parapint/__init__.py
parapint/algorithms/__init__.py
parapint/algorithms/interior_point.py
parapint/algorithms/tests/__init__.py
parapint/algorithms/tests/test_interior_point.py
parapint/algorithms/tests/test_reg.py
parapint/examples/__init__.py
parapint/examples/burgers.py
parapint/examples/interior_point.py
parapint/examples/schur_complement.py
parapint/examples/stochastic.py
parapint/examples/tests/__init__.py
parapint/examples/tests/test_examples.py
parapint/interfaces/__init__.py
parapint/interfaces/interface.py
parapint/interfaces/schur_complement/__init__.py
parapint/interfaces/schur_complement/mpi_sc_ip_interface.py
parapint/interfaces/schur_complement/sc_ip_interface.py
parapint/interfaces/schur_complement/tests/__init__.py
parapint/interfaces/schur_complement/tests/test_mpi_sc_ip_interface.py
parapint/interfaces/schur_complement/tests/test_sc_ip_interface.py
parapint/linalg/__init__.py
parapint/linalg/base_linear_solver_interface.py
parapint/linalg/ma27_interface.py
parapint/linalg/mumps_interface.py
parapint/linalg/results.py
parapint/linalg/scipy_interface.py
parapint/linalg/schur_complement/__init__.py
parapint/linalg/schur_complement/explicit_schur_complement.py
parapint/linalg/schur_complement/mpi_explicit_schur_complement.py
parapint/linalg/schur_complement/tests/__init__.py
parapint/linalg/schur_complement/tests/test_explicit_schur_complement.py
parapint/linalg/schur_complement/tests/test_mpi_explicit_schur_complement.py
parapint/linalg/tests/__init__.py
parapint/linalg/tests/test_linear_solvers.py
parapint/linalg/tests/test_realloc.py
parapint-0.4.0.dist-info/LICENSE.md
parapint-0.4.0.dist-info/METADATA
parapint-0.4.0.dist-info/WHEEL
parapint-0.4.0.dist-info/top_level.txt
parapint-0.4.0.dist-info/RECORD
