Metadata-Version: 2.1
Name: parapint
Version: 0.4.0
Summary: Parapint: Parallel NLP algorithms
Home-page: https://github.com/parapint/parapint
Author: Parapint Developers
Maintainer-email: mlbynum@sandia.gov
License: Revised BSD
Platform: UNKNOWN
Classifier: Programming Language :: Python :: 3
Classifier: Programming Language :: Python :: 3.7
Classifier: Programming Language :: Python :: 3.8
Classifier: Programming Language :: Python :: 3.9
Classifier: License :: OSI Approved :: BSD License
Classifier: Operating System :: OS Independent
Requires-Python: >=3.7
License-File: LICENSE.md
Requires-Dist: numpy (>=1.13.0)
Requires-Dist: scipy
Requires-Dist: pyomo (>=6.4)
Requires-Dist: mpi4py
